cpu/processor/e16076_lab5_part3/two_s_complement.v
// Computer Architecture (CO224) - Lab 05
// Design: 2's complement operator of Simple Processor
// Author: Deshan L.A.C

module twoscomplement (REGOUT2,TWOSCOMP);
  input  [7:0]REGOUT2;
  output [7:0]TWOSCOMP;//output for 2's complement result

  reg [7:0]TWOSCOMP;//register to store 2's complement result

  always @(*)
  begin
       TWOSCOMP = (~REGOUT2 + 'b1);//here bits comming from REGOUT2 is inverted and add 1 to it
  end
endmodule

cpu/processor/e16076_lab5_part5/mux_subtract.v
// Computer Architecture (CO224) - Lab 05
// Design: Multiplexer for subtraction of Simple Processor
// Author: Deshan L.A.C

module mux_subtract(SUBMUXSEL, REGOUT2, TWOSCOMP, NONIMMEDIATE);

     input SUBMUXSEL;                  //initialize inputs
     input [7:0]REGOUT2, TWOSCOMP;
     output [7:0]NONIMMEDIATE;         //initialize outputs

     reg [7:0]NONIMMEDIATE;            //this is named as this because this is the non immediate value to the next multiplexer

     always @ (*)
     begin
         if(SUBMUXSEL == 1)
         begin
		NONIMMEDIATE = TWOSCOMP;//if it is a subtraction then operate 2's complement
         end
         else if(SUBMUXSEL == 0)
         begin
		NONIMMEDIATE = REGOUT2;//if not give the original value
         end
     end
endmodule

cpu/processor/e16076_lab5_part3/mux_immediate.v
// Computer Architecture (CO224) - Lab 05
// Design: Multiplexer for immediate value selection of Simple Processor
// Author: Deshan L.A.C

module mux_immediate(IMMUXSEL, IMMEDIATE, NONIMMEDIATE, OPERAND1);

     input IMMUXSEL;                    //initialize inputs
     input [7:0]IMMEDIATE, NONIMMEDIATE;//here inputs are immediate and non immediate values
     output [7:0]OPERAND1;              //initialize outputs

     reg [7:0]OPERAND1;

     always @ (*)
     begin
         if(IMMUXSEL == 1)
         begin
		OPERAND1 = IMMEDIATE;//if loadi then immediate value is loaded
         end
         else if(IMMUXSEL == 0)
         begin
		OPERAND1 = NONIMMEDIATE;//if not output of the subtract multipleser is loaded
         end
     end
endmodule

cpu/processor/e16076_lab5_part3/alu.v
// Computer Architecture (CO224) - Lab 05
// Design: ALU of Simple Processor
// Author: Deshan L.A.C

module alu(DATA1, DATA2, RESULT, SELECT);//just as method

        //ports declaration
	input [0:7]DATA1;           //initialize inputs for operand1
        input [0:7]DATA2;           //initialize inputs for operand2
        input [0:2]SELECT;          //select the operation
	output [0:7]RESULT;         //initialize outputs
        
        reg [0:7]RESULT;//reg is used as data type for variables to which values are assigned
	
	always @ (DATA1, DATA2, SELECT)//to run always when the arguments get changed   
	begin 
                case(SELECT)
                        3'b000    :
			begin 
				#1;                          //giving related timing delay
				RESULT = DATA2;             // If selection=000, output is taken by loadi, mov functions
			end
                        3'b001    : 
			begin
				#2;                           //giving related timing delay
				RESULT = DATA1 + DATA2;     // If selection=001, output is taken by add, sub functions
			end
                        3'b010    : 
			begin
				#1;                          //giving related timing delay
				RESULT = DATA1 & DATA2;     // If selection=010, output is taken by and functions
			end
			3'b011    : 
			begin
				#1;                           //giving related timing delay
				RESULT = DATA1 | DATA2;     // If selection=011, output is taken by or functions
			end
                        default   : 
			begin
				RESULT = 8'bX ;             // If selection is anything else, out is reserved so it is put 'don't cares' 
			end 
                endcase  
       end	
endmodule

cpu/processor/e16076_lab5_part3/reg_file.v
// Computer Architecture (CO224) - Lab 05
// Design: Register file of Simple Processor
// Author: Deshan L.A.C

module reg_file (IN, OUT1, OUT2, INADDRESS, OUT1ADDRESS, OUT2ADDRESS, WRITE, CLK, RESET);//just as method

        //ports declaration
	//initialize outputs and these names are as given in pdf
        output [7:0]OUT1;           
        output [7:0]OUT2;
	//initialize inputs
	input [7:0]IN;
	input [2:0]INADDRESS;         
	input [2:0]OUT1ADDRESS; 
	input [2:0]OUT2ADDRESS;
	input WRITE;
        input CLK;
        input RESET; 

        reg [7:0]OUT1;//reg is used as data type for variables to which values are assigned
	reg [7:0]OUT2;
	reg [7:0] REGISTERS[0:7];
	integer i;//for the 'for loop'
		
        always @ (*) //get change level triggerd  
	begin
	       if(RESET == 1)// when reset is 1 all the registers get the value 0 and reset is level triggered
	       begin
		   #2;  //registers reset delay
		   for (i=0; i<8; i=i+1)//this is done in a loop
		   begin
		       REGISTERS[i]=8'b0;// all registers getting 0
		   end
	       end
        end	       
	always @ (posedge CLK) //write is happened at positive edge of the clock      
	begin
	       if (WRITE == 1 && RESET == 0)  //this happen when write is enabled and registers are not reseting
               begin
		   #2;  //registers write delay
                   REGISTERS[INADDRESS] <= IN; //values get assigned to registers in the file
               end
        end				              
        
	always @ (REGISTERS[OUT1ADDRESS] , REGISTERS[OUT2ADDRESS])//to run always when the input values get changed
	begin 
	      #2;//registers read delay	
              OUT1 = REGISTERS[OUT1ADDRESS];  //read values get assigned
              OUT2 = REGISTERS[OUT2ADDRESS];   
        end 	
endmodule

cpu/processor/e16076_lab5_part3/control_unit.v
// Computer Architecture (CO224) - Lab 05
// Design: control unit of Simple Processor
// Author: Deshan L.A.C

module control_unit(OPCODE, ALUOP, WRITEENABLE, SUBMUXSEL, IMMUXSEL);

     //ports declaration
    input [7:0]OPCODE;           
    output [2:0]ALUOP;               //initialize outputs
    output WRITEENABLE, SUBMUXSEL, IMMUXSEL;
    //register declaration
    reg [2:0]ALUOP;
    reg WRITEENABLE, SUBMUXSEL, IMMUXSEL; 
    //here according to the opcode operation write enable(WRITEENABLE) and multiplexer selections(SUBMUXSEL,IMMUXSEL) are outputing all ALUOP are given in pdf
    always @ (*)//to run always depending on all
    begin
         #1;//1 time unit is given to this 
         case(OPCODE)
              8'b00000000:
	      begin 
		   ALUOP = 3'b000;
		   WRITEENABLE = 1;//write enable is done
		   SUBMUXSEL = 0;//no 2's complement is happen
	           IMMUXSEL = 1;// for loadi to get immediate value
	      end               //following are also same as enabling and not enabling
              8'b00000001: 
	      begin
		   ALUOP = 3'b000;
		   WRITEENABLE = 1;
		   SUBMUXSEL = 0;
	           IMMUXSEL = 0;
	      end
              8'b00000010: 
	      begin
		   ALUOP = 3'b001;
		   WRITEENABLE = 1;
		   SUBMUXSEL = 0;
	           IMMUXSEL = 0;
	      end
              8'b00000011: 
              begin
		   ALUOP = 3'b001;
		   WRITEENABLE = 1;
		   SUBMUXSEL = 1;// for subtract to get 2's complement value
	           IMMUXSEL = 0;
	      end
	      8'b00000100: 
              begin
		   ALUOP = 3'b010;
		   WRITEENABLE = 1;
		   SUBMUXSEL = 0;
	           IMMUXSEL = 0;
	      end
              8'b00000101: 
              begin
		   ALUOP = 3'b011;
		   WRITEENABLE = 1;
		   SUBMUXSEL = 0;
	           IMMUXSEL = 0;
	      end
              default   : 
	      begin
	           ALUOP = 3'bX;//these are for other reserved controls
		   WRITEENABLE = 0;
		   SUBMUXSEL = 0;
	           IMMUXSEL = 0;	 
	      end 
        endcase  
    end
endmodule

cpu/processor/e16076_lab5_part3/cpu.v
// Computer Architecture (CO224) - Lab 05
// Design: CPU of Simple Processor
// Author: Deshan L.A.C

module cpu(CLK, RESET, INSTRUCTION, PC);
     //these all names are accoding to the project names
     input CLK, RESET;           //initialize inputs
     input [31:0]INSTRUCTION;
     output [31:0]PC;         //initialize outputs
     
     reg [31:0]PC;
     reg [7:0]STORE, OPCODE, DESTINATION, SOURCE1, SOURCE2;
     reg [2:0]WRITEREG, READREG1, READREG2;
     wire WRITEENABLE, SUBMUXSEL, IMMUXSEL;//SUBMUXSEL--->multiplexer for selecting 2's complement or not, IMMUXSEL--->multiplexer for selecting immediate value or registered read value 
     wire [2:0]ALUOP;
     wire [7:0]RESULT, REGOUT1, REGOUT2, NONIMMEDIATE,OPERAND1,TWOSCOMP;

     //connecting to each module
     control_unit control(OPCODE, ALUOP, WRITEENABLE, SUBMUXSEL, IMMUXSEL);
     reg_file regfile(RESULT, REGOUT1, REGOUT2, WRITEREG, READREG1, READREG2, WRITEENABLE, CLK, RESET);
     alu alupart(REGOUT1, OPERAND1, RESULT, ALUOP);
     mux_immediate muximmediate(IMMUXSEL, SOURCE2, NONIMMEDIATE, OPERAND1);
     mux_subtract muxsubtract(SUBMUXSEL, REGOUT2, TWOSCOMP, NONIMMEDIATE);
     twoscomplement mytwoscomplement(REGOUT2,TWOSCOMP);

     always @ (posedge CLK)//writing to pc when reset is not high is done at positive clock edge and having 1 time delay
     begin
     	if(RESET == 0)
     	begin
            #1;	 
            PC = STORE;
     	end 
	//else
	//begin 
            //PC = -4;
     	//end
     end

     always @ (*)//resting pc when reset is high is done at asynchronously and having 1 time delay
     begin
        if(RESET == 1)
     	begin
            #1;	 
            PC = -4;
     	end 
     end

     always @ (*)//updating the pc value parallaly to Instruction Memory Read and having 2 time delay
     begin
     	#2;
        STORE = PC+4;//this is extra register to do this parallaly to store updated value 
     end

     always @ (*)
     begin
     	//#1;//this is decoding
        {OPCODE, DESTINATION, SOURCE1, SOURCE2} = INSTRUCTION;//Decode process having 1 time delay 
        WRITEREG = DESTINATION;//getting least bits
        READREG1 = SOURCE1;//getting least bits
        READREG2 = SOURCE2;//getting least bits
     end
endmodule

cpu/processor/e16076_lab5_part3/cpu_tb.v
// Computer Architecture (CO224) - Lab 05
// Design: Testbench of Simple Processor
// Author: Deshan L.A.C

module cpu_tb;//this is the register file
    //initialize the registers
    reg CLK, RESET;
    reg [31:0]INSTRUCTION;//32 bit size instruction
    wire [31:0] PC;//to get all 1024 address
    reg [7:0] REGISTERS[0:1023];//register is having 1024 elements and each is size 8 bit
    
    cpu mycpu(CLK, RESET, INSTRUCTION, PC);
       
    initial
    begin
        //these are instructions final answers is 4
        /*{REGISTERS[0],REGISTERS[1],REGISTERS[2],REGISTERS[3]} = 32'b00000000000000010000000000000101;//loadi 1 0x05
        {REGISTERS[4],REGISTERS[5],REGISTERS[6],REGISTERS[7]} = 32'b00000001000001110000000000000001;//mov 7 1
        {REGISTERS[8],REGISTERS[9],REGISTERS[10],REGISTERS[11]} = 32'b00000000000000100000000000000111;//loadi 2 0x07
        {REGISTERS[12],REGISTERS[13],REGISTERS[14],REGISTERS[15]} = 32'b00000001000001100000000000000010;//mov 6 2
        {REGISTERS[16],REGISTERS[17],REGISTERS[18],REGISTERS[19]} = 32'b00000010000000110000000100000010;//add 3 1 2
        {REGISTERS[20],REGISTERS[21],REGISTERS[22],REGISTERS[23]} = 32'b00000001000001000000000000000011;//mov 4 3

        {REGISTERS[24],REGISTERS[25],REGISTERS[26],REGISTERS[27]} = 32'b00000011000000000000011000000111;//sub 0 6 7
        {REGISTERS[28],REGISTERS[29],REGISTERS[30],REGISTERS[31]} = 32'b00000001000000010000000000000000;//mov 1 0
        {REGISTERS[32],REGISTERS[33],REGISTERS[34],REGISTERS[35]} = 32'b00000011000000100000011100000110;//sub 2 7 6
        {REGISTERS[36],REGISTERS[37],REGISTERS[38],REGISTERS[39]} = 32'b00000001000000010000000000000010;//mov 1 2
        {REGISTERS[40],REGISTERS[41],REGISTERS[42],REGISTERS[43]} = 32'b00000011000001010000000000000001;//sub 5 0 1
        {REGISTERS[44],REGISTERS[45],REGISTERS[46],REGISTERS[47]} = 32'b00000001000000000000000000000101;//mov 0 5       
*/
{REGISTERS[0],REGISTERS[1],REGISTERS[2],REGISTERS[3]} = 32'b00000000000000010000000000000101;//loadi 1 0x05
        {REGISTERS[4],REGISTERS[5],REGISTERS[6],REGISTERS[7]} = 32'b00000001000001110000000000000001;//mov 7 1
        {REGISTERS[8],REGISTERS[9],REGISTERS[10],REGISTERS[11]} = 32'b00000000000000100000000000000111;//loadi 2 0x07
        {REGISTERS[12],REGISTERS[13],REGISTERS[14],REGISTERS[15]} = 32'b00000001000001100000000000000010;//mov 6 2
        {REGISTERS[16],REGISTERS[17],REGISTERS[18],REGISTERS[19]} = 32'b00000010000000110000000100000010;//add 3 1 2
        {REGISTERS[20],REGISTERS[21],REGISTERS[22],REGISTERS[23]} = 32'b00000001000001000000000000000011;//mov 4 3

        CLK = 1'b1;

        // generate files needed to plot the waveform using GTKWave
        $dumpfile("cpu_wavedata.vcd");
		$dumpvars(0, cpu_tb);
        
        // assign values with time to input signals to see output 
        RESET = 1'b1;//initially reset all
        #2;
        RESET = 1'b0;
        #40;
        RESET = 1'b1;//in mid reset all
        #2;
        RESET = 1'b0;
        #140;
        $finish;
    end
    
    // clock signal generation
    always
        #5 CLK = ~CLK;
    
    always @ (PC)//Instruction Memory Read
     begin
	  #2;//time delay for this
	  INSTRUCTION = {REGISTERS[PC],REGISTERS[PC+1],REGISTERS[PC+2],REGISTERS[PC+3]};//getting the instruction according to the pc value
     end
     
endmodule

cpu/processor/e16076_lab5_part3/cpu_wavedata.vcd
$date
	Sun May 10 22:06:54 2020
$end
$version
	Icarus Verilog
$end
$timescale
	1s
$end
$scope module cpu_tb $end
$var wire 32 ! PC [31:0] $end
$var reg 1 " CLK $end
$var reg 32 # INSTRUCTION [31:0] $end
$var reg 1 $ RESET $end
$scope module mycpu $end
$var wire 1 " CLK $end
$var wire 32 % INSTRUCTION [31:0] $end
$var wire 1 $ RESET $end
$var wire 1 & WRITEENABLE $end
$var wire 8 ' TWOSCOMP [7:0] $end
$var wire 1 ( SUBMUXSEL $end
$var wire 8 ) RESULT [7:0] $end
$var wire 8 * REGOUT2 [7:0] $end
$var wire 8 + REGOUT1 [7:0] $end
$var wire 8 , OPERAND1 [7:0] $end
$var wire 8 - NONIMMEDIATE [7:0] $end
$var wire 1 . IMMUXSEL $end
$var wire 3 / ALUOP [2:0] $end
$var reg 8 0 DESTINATION [7:0] $end
$var reg 8 1 OPCODE [7:0] $end
$var reg 32 2 PC [31:0] $end
$var reg 3 3 READREG1 [2:0] $end
$var reg 3 4 READREG2 [2:0] $end
$var reg 8 5 SOURCE1 [7:0] $end
$var reg 8 6 SOURCE2 [7:0] $end
$var reg 8 7 STORE [7:0] $end
$var reg 3 8 WRITEREG [2:0] $end
$scope module alupart $end
$var wire 3 9 SELECT [0:2] $end
$var wire 8 : DATA2 [0:7] $end
$var wire 8 ; DATA1 [0:7] $end
$var reg 8 < RESULT [0:7] $end
$upscope $end
$scope module control $end
$var wire 8 = OPCODE [7:0] $end
$var reg 3 > ALUOP [2:0] $end
$var reg 1 . IMMUXSEL $end
$var reg 1 ( SUBMUXSEL $end
$var reg 1 & WRITEENABLE $end
$upscope $end
$scope module muximmediate $end
$var wire 8 ? IMMEDIATE [7:0] $end
$var wire 1 . IMMUXSEL $end
$var wire 8 @ NONIMMEDIATE [7:0] $end
$var reg 8 A OPERAND1 [7:0] $end
$upscope $end
$scope module muxsubtract $end
$var wire 1 ( SUBMUXSEL $end
$var wire 8 B TWOSCOMP [7:0] $end
$var wire 8 C REGOUT2 [7:0] $end
$var reg 8 D NONIMMEDIATE [7:0] $end
$upscope $end
$scope module mytwoscomplement $end
$var wire 8 E REGOUT2 [7:0] $end
$var reg 8 F TWOSCOMP [7:0] $end
$upscope $end
$scope module regfile $end
$var wire 1 " CLK $end
$var wire 8 G IN [7:0] $end
$var wire 3 H INADDRESS [2:0] $end
$var wire 3 I OUT1ADDRESS [2:0] $end
$var wire 3 J OUT2ADDRESS [2:0] $end
$var wire 1 $ RESET $end
$var wire 1 & WRITE $end
$var reg 8 K OUT1 [7:0] $end
$var reg 8 L OUT2 [7:0] $end
$var integer 32 M i [31:0] $end
$upscope $end
$upscope $end
$upscope $end
$enddefinitions $end
#0
$dumpvars
bx M
bx L
bx K
bx J
bx I
bx H
bx G
bx F
bx E
bx D
bx C
bx B
bx A
bx @
bx ?
bx >
bx =
bx <
bx ;
bx :
bx 9
bx 8
bx 7
bx 6
bx 5
bx 4
bx 3
bx 2
bx 1
bx 0
bx /
x.
bx -
bx ,
bx +
bx *
bx )
x(
bx '
x&
bx %
1$
bx #
1"
bx !
$end
#1
b11111111111111111111111111111100 !
b11111111111111111111111111111100 2
#2
b1000 M
0$
#3
b0 7
#5
0"
#10
1"
#11
b0 !
b0 2
#13
b101 4
b101 J
b0 3
b0 I
b1 8
b1 H
b0 1
b0 =
b1 0
b0 5
b101 6
b101 ?
b100 7
b10000000000000101 #
b10000000000000101 %
#14
b101 ,
b101 :
b101 A
1.
0(
1&
b0 /
b0 9
b0 >
#15
b0 -
b0 @
b0 D
b0 '
b0 B
b0 F
b101 )
b101 <
b101 G
b0 *
b0 C
b0 E
b0 L
b0 +
b0 ;
b0 K
0"
#20
1"
#21
b100 !
b100 2
#23
b1 ,
b1 :
b1 A
b1 4
b1 J
b111 8
b111 H
b1 1
b1 =
b111 0
b1 6
b1 ?
b1000001110000000000000001 #
b1000001110000000000000001 %
b1000 7
#24
b0 ,
b0 :
b0 A
b1 )
b1 <
b1 G
0.
#25
b101 ,
b101 :
b101 A
b101 -
b101 @
b101 D
b11111011 '
b11111011 B
b11111011 F
b0 )
b0 <
b0 G
b101 *
b101 C
b101 E
b101 L
0"
#26
b101 )
b101 <
b101 G
#30
1"
#31
b1000 !
b1000 2
#33
b111 4
b111 J
b10 8
b10 H
b0 1
b0 =
b10 0
b111 6
b111 ?
b1100 7
b100000000000000111 #
b100000000000000111 %
#34
b111 ,
b111 :
b111 A
1.
#35
b111 )
b111 <
b111 G
0"
#40
1"
#41
b1100 !
b1100 2
#42
1$
#43
b10 ,
b10 :
b10 A
b10 4
b10 J
b110 8
b110 H
b1 1
b1 =
b110 0
b10 6
b10 ?
b11111111111111111111111111111100 !
b11111111111111111111111111111100 2
b1000001100000000000000010 #
b1000001100000000000000010 %
b10000 7
#44
b101 ,
b101 :
b101 A
b10 )
b10 <
b10 G
0.
b1000 M
0$
#45
b0 ,
b0 :
b0 A
b0 -
b0 @
b0 D
b0 '
b0 B
b0 F
bx 4
bx J
bx 3
bx I
bx 8
bx H
bx 1
bx =
bx 0
bx 5
bx 6
bx ?
b101 )
b101 <
b101 G
b0 *
b0 C
b0 E
b0 L
b0 7
bx #
bx %
0"
#46
b0 )
b0 <
b0 G
0&
bx /
bx 9
bx >
#47
bx ,
bx :
bx A
bx -
bx @
bx D
bx '
bx B
bx F
bx )
bx <
bx G
bx *
bx C
bx E
bx L
bx +
bx ;
bx K
#50
1"
#51
b0 !
b0 2
#53
b101 4
b101 J
b0 3
b0 I
b1 8
b1 H
b0 1
b0 =
b1 0
b0 5
b101 6
b101 ?
b10000000000000101 #
b10000000000000101 %
b100 7
#54
b101 ,
b101 :
b101 A
1.
1&
b0 /
b0 9
b0 >
#55
b0 -
b0 @
b0 D
b0 '
b0 B
b0 F
b101 )
b101 <
b101 G
b0 *
b0 C
b0 E
b0 L
b0 +
b0 ;
b0 K
0"
#60
1"
#61
b100 !
b100 2
#63
b1 ,
b1 :
b1 A
b1 4
b1 J
b111 8
b111 H
b1 1
b1 =
b111 0
b1 6
b1 ?
b1000 7
b1000001110000000000000001 #
b1000001110000000000000001 %
#64
b0 ,
b0 :
b0 A
b1 )
b1 <
b1 G
0.
#65
b101 ,
b101 :
b101 A
b101 -
b101 @
b101 D
b11111011 '
b11111011 B
b11111011 F
b0 )
b0 <
b0 G
b101 *
b101 C
b101 E
b101 L
0"
#66
b101 )
b101 <
b101 G
#70
1"
#71
b1000 !
b1000 2
#73
b111 4
b111 J
b10 8
b10 H
b0 1
b0 =
b10 0
b111 6
b111 ?
b100000000000000111 #
b100000000000000111 %
b1100 7
#74
b111 ,
b111 :
b111 A
1.
#75
b111 )
b111 <
b111 G
0"
#80
1"
#81
b1100 !
b1100 2
#83
b10 ,
b10 :
b10 A
b10 4
b10 J
b110 8
b110 H
b1 1
b1 =
b110 0
b10 6
b10 ?
b10000 7
b1000001100000000000000010 #
b1000001100000000000000010 %
#84
b101 ,
b101 :
b101 A
b10 )
b10 <
b10 G
0.
#85
b111 ,
b111 :
b111 A
b111 -
b111 @
b111 D
b11111001 '
b11111001 B
b11111001 F
b101 )
b101 <
b101 G
b111 *
b111 C
b111 E
b111 L
0"
#86
b111 )
b111 <
b111 G
#90
1"
#91
b10000 !
b10000 2
#93
b1 3
b1 I
b11 8
b11 H
b10 1
b10 =
b11 0
b1 5
b10000000110000000100000010 #
b10000000110000000100000010 %
b10100 7
#94
b1 /
b1 9
b1 >
#95
b101 +
b101 ;
b101 K
0"
#96
b1100 )
b1100 <
b1100 G
#100
1"
#101
b10100 !
b10100 2
#103
b11 4
b11 J
b0 3
b0 I
b100 8
b100 H
b1 1
b1 =
b100 0
b0 5
b11 6
b11 ?
b11000 7
b1000001000000000000000011 #
b1000001000000000000000011 %
#104
b0 /
b0 9
b0 >
#105
b1100 ,
b1100 :
b1100 A
b1100 -
b1100 @
b1100 D
b11110100 '
b11110100 B
b11110100 F
b111 )
b111 <
b111 G
b1100 *
b1100 C
b1100 E
b1100 L
b0 +
b0 ;
b0 K
0"
#106
b1100 )
b1100 <
b1100 G
#110
1"
#111
b11000 !
b11000 2
#113
bx 4
bx J
bx 3
bx I
bx 8
bx H
bx 1
bx =
bx 0
bx 5
bx 6
bx ?
bx #
bx %
b11100 7
#114
bx )
bx <
bx G
0&
bx /
bx 9
bx >
#115
bx ,
bx :
bx A
bx -
bx @
bx D
bx '
bx B
bx F
bx *
bx C
bx E
bx L
bx +
bx ;
bx K
0"
#120
1"
#121
b11100 !
b11100 2
#123
b100000 7
#125
0"
#130
1"
#131
b100000 !
b100000 2
#133
b100100 7
#135
0"
#140
1"
#141
b100100 !
b100100 2
#143
b101000 7
#145
0"
#150
1"
#151
b101000 !
b101000 2
#153
b101100 7
#155
0"
#160
1"
#161
b101100 !
b101100 2
#163
b110000 7
#165
0"
#170
1"
#171
b110000 !
b110000 2
#173
b110100 7
#175
0"
#180
1"
#181
b110100 !
b110100 2
#183
b111000 7
