cpu/processor/e16076_lab5_part4/pc_selection.v
// Computer Architecture (CO224) - Lab 05
// Design: pc value selecting of Simple Processor
// Author: Deshan L.A.C

module pc_selection (JUMP, BEQ, ZERO, SEL);
    
    input JUMP, BEQ, ZERO;//inputs 
    output  SEL;          //outputs just wires

    assign SEL = JUMP | BEQ & ZERO;//(jump) or (beq and zero) this calculate the selection 
 
endmodule

cpu/memory/muxpc.v
// Computer Architecture (CO224) - Lab 05
// Design: pc slect multiplexer of Simple Processor
// Author: Deshan L.A.C

module MUXPC (STORE, PCIN, SEL, PCOUT);
    
    input SEL;              //inputs for the multiplexer
    input [31:0] STORE, PCIN;
    output reg [31:0] PCOUT;//output and register for the multiplexer

   //assign PCOUT = (1'bX)?PCIN:STORE;  //this not work for the dont care conditions
    always @ (*)//resting pc when reset is high is done at asynchronously and having 1 time delay
     begin
        if(SEL == 1)//selection is one only for jump or branch if equal occasions
     	   PCOUT = PCIN;//this happen only when jump or branch if equal occasions are happened
        else
           PCOUT = STORE;//for other events
     end
 
endmodule

cpu/memory/adder.v
// Computer Architecture (CO224) - Lab 05
// Design: adder of Simple Processor
// Author: Deshan L.A.C

module adder(STORE,EXTNDED_SHIFT, PCIN);
    input [31:0] STORE, EXTNDED_SHIFT;//inputs for the adder
    output [31:0] PCIN;               //outputs

    assign #2 PCIN = STORE + EXTNDED_SHIFT;//here with #2 delay (pc+4)+extended and shift valve is added
    
endmodule

cpu/processor/e16076_lab5_part5/signextendshift.v
// Computer Architecture (CO224) - Lab 05
// Design: sign extender with keft shift of Simple Processor
// Author: Deshan L.A.C

module SignExtendAndShift(UNEXTENDED,EXTNDED_SHIFT);
    input [7:0] UNEXTENDED;
    output reg[31:0] EXTNDED_SHIFT;

    //assign EXTNDED_SHIFT = { {24{UNEXTENDED[7]}}, UNEXTENDED }<<2;
    always @(*)//by just adding wires
    begin
         EXTNDED_SHIFT = { {24{UNEXTENDED[7]}}, UNEXTENDED };//sign extension is done here
         EXTNDED_SHIFT = {EXTNDED_SHIFT[29:0],2'b00 };       //multiply by 4 or <<2 is done by giving two zeros to the end of the wire
    end
endmodule

cpu/processor/e16076_lab5_part3/two_s_complement.v
// Computer Architecture (CO224) - Lab 05
// Design: 2's complement operator of Simple Processor
// Author: Deshan L.A.C

module twoscomplement (REGOUT2,TWOSCOMP);
  input  [7:0]REGOUT2;
  output [7:0]TWOSCOMP;//output for 2's complement result

  reg [7:0]TWOSCOMP;//register to store 2's complement result

  always @(*)
  begin
       TWOSCOMP = (~REGOUT2 + 'b1);//here bits comming from REGOUT2 is inverted and add 1 to it
  end
endmodule

cpu/processor/e16076_lab5_part5/mux_subtract.v
// Computer Architecture (CO224) - Lab 05
// Design: Multiplexer for subtraction of Simple Processor
// Author: Deshan L.A.C

module mux_subtract(SUBMUXSEL, REGOUT2, TWOSCOMP, NONIMMEDIATE);

     input SUBMUXSEL;                  //initialize inputs
     input [7:0]REGOUT2, TWOSCOMP;
     output [7:0]NONIMMEDIATE;         //initialize outputs

     reg [7:0]NONIMMEDIATE;            //this is named as this because this is the non immediate value to the next multiplexer

     always @ (*)
     begin
         if(SUBMUXSEL == 1)
         begin
		NONIMMEDIATE = TWOSCOMP;//if it is a subtraction then operate 2's complement
         end
         else if(SUBMUXSEL == 0)
         begin
		NONIMMEDIATE = REGOUT2;//if not give the original value
         end
     end
endmodule

cpu/processor/e16076_lab5_part3/mux_immediate.v
// Computer Architecture (CO224) - Lab 05
// Design: Multiplexer for immediate value selection of Simple Processor
// Author: Deshan L.A.C

module mux_immediate(IMMUXSEL, IMMEDIATE, NONIMMEDIATE, OPERAND1);

     input IMMUXSEL;                    //initialize inputs
     input [7:0]IMMEDIATE, NONIMMEDIATE;//here inputs are immediate and non immediate values
     output [7:0]OPERAND1;              //initialize outputs

     reg [7:0]OPERAND1;

     always @ (*)
     begin
         if(IMMUXSEL == 1)
         begin
		OPERAND1 = IMMEDIATE;//if loadi then immediate value is loaded
         end
         else if(IMMUXSEL == 0)
         begin
		OPERAND1 = NONIMMEDIATE;//if not output of the subtract multipleser is loaded
         end
     end
endmodule

cpu/processor/e16076_lab5_part5/alu.v
// Computer Architecture (CO224) - Lab 05
// Design: ALU of Simple Processor
// Author: Deshan L.A.C

module alu(DATA1, DATA2, RESULT, ZERO, SELECT);//just as method

        //ports declaration
	input [0:7]DATA1;           //initialize inputs for operand1
        input [0:7]DATA2;           //initialize inputs for operand2
        input [0:2]SELECT;          //select the operation
	output [0:7]RESULT;         //initialize outputs
        output ZERO;
        
        reg [0:7]RESULT;//reg is used as data type for variables to which values are assigned

        assign ZERO = ~(|RESULT);//always inverse of the result is assigned to the zero which is a one bit signal
	
	always @ (DATA1, DATA2, SELECT)//to run always when the arguments get changed   
	begin 
                case(SELECT)
                        3'b000    :
			begin 
				#1;                          //giving related timing delay
				RESULT = DATA2;             // If selection=000, output is taken by loadi, mov functions
			end
                        3'b001    : 
			begin
				#2;                           //giving related timing delay
				RESULT = DATA1 + DATA2;     // If selection=001, output is taken by add, sub functions
			end
                        3'b010    : 
			begin
				#1;                          //giving related timing delay
				RESULT = DATA1 & DATA2;     // If selection=010, output is taken by and functions
			end
			3'b011    : 
			begin
				#1;                           //giving related timing delay
				RESULT = DATA1 | DATA2;     // If selection=011, output is taken by or functions
			end
                        default   : 
			begin
				RESULT = 8'bX ;             // If selection is anything else, out is reserved so it is put 'don't cares' 
			end 
                endcase  
       end	
endmodule

cpu/processor/e16076_lab5_part3/reg_file.v
// Computer Architecture (CO224) - Lab 05
// Design: Register file of Simple Processor
// Author: Deshan L.A.C

module reg_file (IN, OUT1, OUT2, INADDRESS, OUT1ADDRESS, OUT2ADDRESS, WRITE, CLK, RESET);//just as method

        //ports declaration
	//initialize outputs and these names are as given in pdf
        output [7:0]OUT1;           
        output [7:0]OUT2;
	//initialize inputs
	input [7:0]IN;
	input [2:0]INADDRESS;         
	input [2:0]OUT1ADDRESS; 
	input [2:0]OUT2ADDRESS;
	input WRITE;
        input CLK;
        input RESET; 

        reg [7:0]OUT1;//reg is used as data type for variables to which values are assigned
	reg [7:0]OUT2;
	reg [7:0] REGISTERS[0:7];
	integer i;//for the 'for loop'
		
        always @ (*) //get change level triggerd  
	begin
	       if(RESET == 1)// when reset is 1 all the registers get the value 0 and reset is level triggered
	       begin
		   #2;  //registers reset delay
		   for (i=0; i<8; i=i+1)//this is done in a loop
		   begin
		       REGISTERS[i]=8'b0;// all registers getting 0
		   end
	       end
        end	       
	always @ (posedge CLK) //write is happened at positive edge of the clock      
	begin
	       if (WRITE == 1 && RESET == 0)  //this happen when write is enabled and registers are not reseting
               begin
		   #2;  //registers write delay
                   REGISTERS[INADDRESS] <= IN; //values get assigned to registers in the file
               end
        end				              
        
	always @ (REGISTERS[OUT1ADDRESS] , REGISTERS[OUT2ADDRESS])//to run always when the input values get changed
	begin 
	      #2;//registers read delay	
              OUT1 = REGISTERS[OUT1ADDRESS];  //read values get assigned
              OUT2 = REGISTERS[OUT2ADDRESS];   
        end 	
endmodule

cpu/processor/e16076_lab5_part4/control_unit.v
// Computer Architecture (CO224) - Lab 05
// Design: control unit of Simple Processor
// Author: Deshan L.A.C

module control_unit(OPCODE, ALUOP, WRITEENABLE, SUBMUXSEL, IMMUXSEL, JUMP, BEQ);

     //ports declaration
    input [7:0]OPCODE;           
    output [2:0]ALUOP;               //initialize outputs
    output WRITEENABLE, SUBMUXSEL, IMMUXSEL, JUMP, BEQ;
    //register declaration
    reg [2:0]ALUOP;
    reg WRITEENABLE, SUBMUXSEL, IMMUXSEL, JUMP, BEQ; 
    //here according to the opcode operation write enable(WRITEENABLE) and multiplexer selections(SUBMUXSEL,IMMUXSEL) are outputing all ALUOP are given in pdf
    //here JUMP and BEQ are for j and beq
    always @ (*)//to run always depending on all
    begin
         #1;//1 time unit is given to this 
         case(OPCODE)
              8'b00000000:
	      begin 
		   ALUOP = 3'b000;
		   WRITEENABLE = 1;//write enable is done
		   SUBMUXSEL = 0;//no 2's complement is happen
	           IMMUXSEL = 1;// for loadi to get immediate value
                   JUMP = 0;
                   BEQ = 0;
	      end               //following are also same as enabling and not enabling
              8'b00000001: 
	      begin
		   ALUOP = 3'b000;
		   WRITEENABLE = 1;
		   SUBMUXSEL = 0;
	           IMMUXSEL = 0;
                   JUMP = 0;
                   BEQ = 0;
	      end
              8'b00000010: 
	      begin
		   ALUOP = 3'b001;
		   WRITEENABLE = 1;
		   SUBMUXSEL = 0;
	           IMMUXSEL = 0;
                   JUMP = 0;
                   BEQ = 0;
	      end
              8'b00000011: 
              begin
		   ALUOP = 3'b001;
		   WRITEENABLE = 1;
		   SUBMUXSEL = 1;// for subtract to get 2's complement value
	           IMMUXSEL = 0;
                   JUMP = 0;
                   BEQ = 0;
	      end
	      8'b00000100: 
              begin
		   ALUOP = 3'b010;
		   WRITEENABLE = 1;
		   SUBMUXSEL = 0;
	           IMMUXSEL = 0;
                   JUMP = 0;
                   BEQ = 0;
	      end
              8'b00000101: 
              begin
		   ALUOP = 3'b011;
		   WRITEENABLE = 1;
		   SUBMUXSEL = 0;
	           IMMUXSEL = 0;
                   JUMP = 0;
                   BEQ = 0;
	      end
              8'b00000110: //for jump
              begin
		   ALUOP = 3'bX;//for jump no alu opcode is given and it is don't care
		   WRITEENABLE = 0;
		   SUBMUXSEL = 0;
	           IMMUXSEL = 0;
                   JUMP = 1;
                   BEQ = 0;
	      end
              8'b00000111: //for branch if equal
              begin
		   ALUOP = 3'b001;
		   WRITEENABLE = 0;
		   SUBMUXSEL = 1;//to check two registers are same subtraction is allowed
	           IMMUXSEL = 0;
                   JUMP = 0;
                   BEQ = 1;
	      end
              default   : 
	      begin
	           ALUOP = 3'bX;//these are for other reserved controls
		   WRITEENABLE = 0;
		   SUBMUXSEL = 0;
	           IMMUXSEL = 0;
                   JUMP = 0;
                   BEQ = 0;	 
	      end 
        endcase  
    end
endmodule

cpu/processor/e16076_lab5_part4/cpu.v
// Computer Architecture (CO224) - Lab 05
// Design: CPU of Simple Processor
// Author: Deshan L.A.C

//import files
`include "control_unit.v"
`include "reg_file.v"
`include "two_s_complement.v"
`include "mux_subtract.v"
`include "mux_immediate.v"
`include "alu.v"
`include "muxpc.v"
`include "pc_selection.v"
`include "signextendshift.v"
`include "adder.v"

module cpu(CLK, RESET, INSTRUCTION, PC);
     //these all names are accoding to the project names
     input CLK, RESET;           //initialize inputs
     input [31:0]INSTRUCTION;
     output [31:0]PC;         //initialize outputs
     
     reg [31:0]PC, STORE;
     reg [7:0]OPCODE, DESTINATION, SOURCE1, SOURCE2;
     reg [2:0]WRITEREG, READREG1, READREG2;
     wire WRITEENABLE, SUBMUXSEL, IMMUXSEL, SEL, JUMP, BEQ, ZERO;//SUBMUXSEL->multiplexer for selecting 2's complement or not, IMMUXSEL->multiplexer for selecting immediate value or registered read value 
     wire [2:0]ALUOP;
     wire [7:0]RESULT, REGOUT1, REGOUT2, NONIMMEDIATE,OPERAND1,TWOSCOMP;
     wire [31:0]EXTNDED_SHIFT, PCIN, PCOUT;

     //connecting to each module
     control_unit control(OPCODE, ALUOP, WRITEENABLE, SUBMUXSEL, IMMUXSEL, JUMP, BEQ);
     reg_file regfile(RESULT, REGOUT1, REGOUT2, WRITEREG, READREG1, READREG2, WRITEENABLE, CLK, RESET);
     alu alupart(REGOUT1, OPERAND1, RESULT, ZERO, ALUOP);
     mux_immediate muximmediate(IMMUXSEL, SOURCE2, NONIMMEDIATE, OPERAND1);
     mux_subtract muxsubtract(SUBMUXSEL, REGOUT2, TWOSCOMP, NONIMMEDIATE);
     twoscomplement mytwoscomplement(REGOUT2,TWOSCOMP);
     SignExtendAndShift myseas(DESTINATION, EXTNDED_SHIFT);
     adder myadder(STORE,EXTNDED_SHIFT, PCIN);
     MUXPC myMUXPC(STORE, PCIN, SEL, PCOUT);
     pc_selection mypc_selection(JUMP, BEQ, ZERO, SEL);

     always @ (posedge CLK)//writing to pc when reset is not high is done at positive clock edge and having 1 time delay
     begin
     	if(RESET == 0)
     	begin
            #1;	 
            PC = PCOUT;
     	end 
	//else
	//begin 
            //PC = -4;
     	//end
     end

     always @ (*)//resting pc when reset is high is done at asynchronously and having 1 time delay
     begin
        if(RESET == 1)
     	begin
            #1;	 
            PC = -4;
     	end 
     end

     always @ (*)//updating the pc value parallaly to Instruction Memory Read and having 2 time delay
     begin
     	#2;
        STORE = PC+4;//this is extra register to do this parallaly to store updated value 
     end

     always @ (*)
     begin
     	//#1;//this is decoding
        {OPCODE, DESTINATION, SOURCE1, SOURCE2} = INSTRUCTION;//Decode process having 1 time delay 
        WRITEREG = DESTINATION;//getting least bits
        READREG1 = SOURCE1;//getting least bits
        READREG2 = SOURCE2;//getting least bits
     end
endmodule

cpu/processor/e16076_lab5_part4/cpu_tb.v
// Computer Architecture (CO224) - Lab 05
// Design: Testbench of Simple Processor
// Author: Deshan L.A.C

//import files
`include "cpu.v"

module cpu_tb;//this is the register file
    //initialize the registers
    reg CLK, RESET;
    reg [31:0]INSTRUCTION;//32 bit size instruction
    wire [31:0] PC;//to get all 1024 address
    reg [7:0] REGISTERS[0:1023];//register is having 1024 elements and each is size 8 bit
    
    cpu mycpu(CLK, RESET, INSTRUCTION, PC);
       
    initial
    begin
        //these are instructions final answers is 4
        /*{REGISTERS[0],REGISTERS[1],REGISTERS[2],REGISTERS[3]} = 32'b00000000000000010000000000000101;//loadi 1 0x05
        {REGISTERS[4],REGISTERS[5],REGISTERS[6],REGISTERS[7]} = 32'b00000001000001110000000000000001;//mov 7 1
        {REGISTERS[8],REGISTERS[9],REGISTERS[10],REGISTERS[11]} = 32'b00000000000000100000000000000111;//loadi 2 0x07
        {REGISTERS[12],REGISTERS[13],REGISTERS[14],REGISTERS[15]} = 32'b00000001000001100000000000000010;//mov 6 2
        {REGISTERS[16],REGISTERS[17],REGISTERS[18],REGISTERS[19]} = 32'b00000010000000110000000100000010;//add 3 1 2
        {REGISTERS[20],REGISTERS[21],REGISTERS[22],REGISTERS[23]} = 32'b00000001000001000000000000000011;//mov 4 3
        {REGISTERS[24],REGISTERS[25],REGISTERS[26],REGISTERS[27]} = 32'b00000011000000000000011000000111;//sub 0 6 7
        {REGISTERS[28],REGISTERS[29],REGISTERS[30],REGISTERS[31]} = 32'b00000001000000010000000000000000;//mov 1 0
        {REGISTERS[32],REGISTERS[33],REGISTERS[34],REGISTERS[35]} = 32'b00000011000000100000011100000110;//sub 2 7 6
        {REGISTERS[36],REGISTERS[37],REGISTERS[38],REGISTERS[39]} = 32'b00000001000000010000000000000010;//mov 1 2
        {REGISTERS[40],REGISTERS[41],REGISTERS[42],REGISTERS[43]} = 32'b00000011000001010000000000000001;//sub 5 0 1
        {REGISTERS[44],REGISTERS[45],REGISTERS[46],REGISTERS[47]} = 32'b00000001000000000000000000000101;//mov 0 5       
        */
        {REGISTERS[0],REGISTERS[1],REGISTERS[2],REGISTERS[3]} = 32'b00000000000000010000000000000101;//new instruction set to check the lab 4
        {REGISTERS[4],REGISTERS[5],REGISTERS[6],REGISTERS[7]} = 32'b00000001000000100000000000000001;
        {REGISTERS[8],REGISTERS[9],REGISTERS[10],REGISTERS[11]} = 32'b00000110000000110000000000000000;
        {REGISTERS[12],REGISTERS[13],REGISTERS[14],REGISTERS[15]} = 32'b00000010000001010000000100000010;
        {REGISTERS[16],REGISTERS[17],REGISTERS[18],REGISTERS[19]} = 32'b00000100000001100000000100000010;
        {REGISTERS[20],REGISTERS[21],REGISTERS[22],REGISTERS[23]} = 32'b00000111000000110000000100000011;
        {REGISTERS[24],REGISTERS[25],REGISTERS[26],REGISTERS[27]} = 32'b00000000000000110000000000000100;
        {REGISTERS[28],REGISTERS[29],REGISTERS[30],REGISTERS[31]} = 32'b00000000000001000000000000000100;
        {REGISTERS[32],REGISTERS[33],REGISTERS[34],REGISTERS[35]} = 32'b00000111111110110000001100000100;
        {REGISTERS[36],REGISTERS[37],REGISTERS[38],REGISTERS[39]} = 32'b00000000000001110000000000000111;

        CLK = 1'b1;

        // generate files needed to plot the waveform using GTKWave
        $dumpfile("cpu_wavedata.vcd");
		$dumpvars(0, cpu_tb);
        
        // assign values with time to input signals to see output 
        RESET = 1'b1;//initially reset all
        #2;
        RESET = 1'b0;
        #40;
        RESET = 1'b1;//in mid reset all
        #2;
        RESET = 1'b0;
        #140;
        $finish;
    end
    
    // clock signal generation
    always
        #5 CLK = ~CLK;
    
    always @ (PC)//Instruction Memory Read
     begin
	  #2;//time delay for this
	  INSTRUCTION = {REGISTERS[PC],REGISTERS[PC+1],REGISTERS[PC+2],REGISTERS[PC+3]};//getting the instruction according to the pc value
     end
     
endmodule

cpu/processor/e16076_lab5_part4/cpu_wavedata.vcd
$date
	Sat May 30 20:43:50 2020
$end
$version
	Icarus Verilog
$end
$timescale
	1s
$end
$scope module cpu_tb $end
$var wire 32 ! PC [31:0] $end
$var reg 1 " CLK $end
$var reg 32 # INSTRUCTION [31:0] $end
$var reg 1 $ RESET $end
$scope module mycpu $end
$var wire 1 " CLK $end
$var wire 32 % INSTRUCTION [31:0] $end
$var wire 1 $ RESET $end
$var wire 1 & ZERO $end
$var wire 1 ' WRITEENABLE $end
$var wire 8 ( TWOSCOMP [7:0] $end
$var wire 1 ) SUBMUXSEL $end
$var wire 1 * SEL $end
$var wire 8 + RESULT [7:0] $end
$var wire 8 , REGOUT2 [7:0] $end
$var wire 8 - REGOUT1 [7:0] $end
$var wire 32 . PCOUT [31:0] $end
$var wire 32 / PCIN [31:0] $end
$var wire 8 0 OPERAND1 [7:0] $end
$var wire 8 1 NONIMMEDIATE [7:0] $end
$var wire 1 2 JUMP $end
$var wire 1 3 IMMUXSEL $end
$var wire 32 4 EXTNDED_SHIFT [31:0] $end
$var wire 1 5 BEQ $end
$var wire 3 6 ALUOP [2:0] $end
$var reg 8 7 DESTINATION [7:0] $end
$var reg 8 8 OPCODE [7:0] $end
$var reg 32 9 PC [31:0] $end
$var reg 3 : READREG1 [2:0] $end
$var reg 3 ; READREG2 [2:0] $end
$var reg 8 < SOURCE1 [7:0] $end
$var reg 8 = SOURCE2 [7:0] $end
$var reg 32 > STORE [31:0] $end
$var reg 3 ? WRITEREG [2:0] $end
$scope module alupart $end
$var wire 1 & ZERO $end
$var wire 3 @ SELECT [0:2] $end
$var wire 8 A DATA2 [0:7] $end
$var wire 8 B DATA1 [0:7] $end
$var reg 8 C RESULT [0:7] $end
$upscope $end
$scope module control $end
$var wire 8 D OPCODE [7:0] $end
$var reg 3 E ALUOP [2:0] $end
$var reg 1 5 BEQ $end
$var reg 1 3 IMMUXSEL $end
$var reg 1 2 JUMP $end
$var reg 1 ) SUBMUXSEL $end
$var reg 1 ' WRITEENABLE $end
$upscope $end
$scope module muximmediate $end
$var wire 8 F IMMEDIATE [7:0] $end
$var wire 1 3 IMMUXSEL $end
$var wire 8 G NONIMMEDIATE [7:0] $end
$var reg 8 H OPERAND1 [7:0] $end
$upscope $end
$scope module muxsubtract $end
$var wire 1 ) SUBMUXSEL $end
$var wire 8 I TWOSCOMP [7:0] $end
$var wire 8 J REGOUT2 [7:0] $end
$var reg 8 K NONIMMEDIATE [7:0] $end
$upscope $end
$scope module myMUXPC $end
$var wire 32 L STORE [31:0] $end
$var wire 1 * SEL $end
$var wire 32 M PCIN [31:0] $end
$var reg 32 N PCOUT [31:0] $end
$upscope $end
$scope module myadder $end
$var wire 32 O STORE [31:0] $end
$var wire 32 P PCIN [31:0] $end
$var wire 32 Q EXTNDED_SHIFT [31:0] $end
$upscope $end
$scope module mypc_selection $end
$var wire 1 5 BEQ $end
$var wire 1 2 JUMP $end
$var wire 1 * SEL $end
$var wire 1 & ZERO $end
$upscope $end
$scope module myseas $end
$var wire 8 R UNEXTENDED [7:0] $end
$var reg 32 S EXTNDED_SHIFT [31:0] $end
$upscope $end
$scope module mytwoscomplement $end
$var wire 8 T REGOUT2 [7:0] $end
$var reg 8 U TWOSCOMP [7:0] $end
$upscope $end
$scope module regfile $end
$var wire 1 " CLK $end
$var wire 8 V IN [7:0] $end
$var wire 3 W INADDRESS [2:0] $end
$var wire 8 X OUT1 [7:0] $end
$var wire 3 Y OUT1ADDRESS [2:0] $end
$var wire 8 Z OUT2 [7:0] $end
$var wire 3 [ OUT2ADDRESS [2:0] $end
$var wire 1 $ RESET $end
$var wire 1 ' WRITE $end
$var integer 32 \ i [31:0] $end
$upscope $end
$upscope $end
$upscope $end
$enddefinitions $end
#0
$dumpvars
bx \
bx [
bx Z
bx Y
bx X
bx W
bx V
bx U
bx T
bx S
bx R
bx Q
bx P
bx O
bx N
bx M
bx L
bx K
bx J
bx I
bx H
bx G
bx F
bx E
bx D
bx C
bx B
bx A
bx @
bx ?
bx >
bx =
bx <
bx ;
bx :
bx 9
bx 8
bx 7
bx 6
x5
bx 4
x3
x2
bx 1
bx 0
bx /
bx .
bx -
bx ,
bx +
x*
x)
bx (
x'
x&
bx %
1$
bx #
1"
bx !
$end
#1
b11111111111111111111111111111100 !
b11111111111111111111111111111100 9
#2
b1000 \
0$
#3
b0 .
b0 N
b0 >
b0 L
b0 O
#5
0"
#10
1"
#11
b0 !
b0 9
#13
b100 4
b100 Q
b100 S
b100 .
b100 N
b101 ;
b101 [
b0 :
b0 Y
b1 ?
b1 W
b0 8
b0 D
b1 7
b1 R
b0 <
b101 =
b101 F
b100 >
b100 L
b100 O
b10000000000000101 #
b10000000000000101 %
#14
0*
b101 0
b101 A
b101 H
05
02
13
0)
1'
b0 6
b0 @
b0 E
#15
0&
b0 1
b0 G
b0 K
b0 (
b0 I
b0 U
b101 +
b101 C
b101 V
b1000 /
b1000 M
b1000 P
b0 ,
b0 J
b0 T
b0 Z
b0 -
b0 B
b0 X
0"
#20
1"
#21
b100 !
b100 9
#23
b1000 4
b1000 Q
b1000 S
b1 0
b1 A
b1 H
b1 ;
b1 [
b10 ?
b10 W
b1 8
b1 D
b10 7
b10 R
b1 =
b1 F
b1000 .
b1000 N
b1000000100000000000000001 #
b1000000100000000000000001 %
b1000 >
b1000 L
b1000 O
#24
b0 0
b0 A
b0 H
b1 +
b1 C
b1 V
03
#25
b101 0
b101 A
b101 H
1&
b101 1
b101 G
b101 K
b11111011 (
b11111011 I
b11111011 U
b0 +
b0 C
b0 V
b101 ,
b101 J
b101 T
b101 Z
b10000 /
b10000 M
b10000 P
0"
#26
0&
b101 +
b101 C
b101 V
#30
1"
#31
b1000 !
b1000 9
#33
b1100 4
b1100 Q
b1100 S
b1100 .
b1100 N
b0 ;
b0 [
b11 ?
b11 W
b110 8
b110 D
b11 7
b11 R
b0 =
b0 F
b1100 >
b1100 L
b1100 O
b110000000110000000000000000 #
b110000000110000000000000000 %
#34
b10000 .
b10000 N
x&
1*
bx +
bx C
bx V
12
0'
bx 6
bx @
bx E
#35
b0 0
b0 A
b0 H
b0 1
b0 G
b0 K
b0 (
b0 I
b0 U
b11000 .
b11000 N
b0 ,
b0 J
b0 T
b0 Z
b11000 /
b11000 M
b11000 P
0"
#40
1"
#41
b11000 !
b11000 9
#42
1$
#43
b100 ;
b100 [
b0 8
b0 D
b100 =
b100 F
b11111111111111111111111111111100 !
b11111111111111111111111111111100 9
b110000000000000100 #
b110000000000000100 %
b11100 >
b11100 L
b11100 O
#44
b11100 .
b11100 N
0*
b100 0
b100 A
b100 H
02
13
1'
b0 6
b0 @
b0 E
b1000 \
0$
#45
bx00 4
bx00 Q
bx00 S
bx 0
bx A
bx H
0&
bx ;
bx [
bx :
bx Y
bx ?
bx W
bx 8
bx D
bx 7
bx R
bx <
bx =
bx F
b0 .
b0 N
b100 +
b100 C
b100 V
b0 >
b0 L
b0 O
bx #
bx %
b101000 /
b101000 M
b101000 P
0"
#46
x&
b0 0
b0 A
b0 H
bx +
bx C
bx V
03
0'
bx 6
bx @
bx E
#47
bx 0
bx A
bx H
bx 1
bx G
bx K
bx (
bx I
bx U
bx ,
bx J
bx T
bx Z
bx -
bx B
bx X
bx /
bx M
bx P
#50
1"
#51
b0 !
b0 9
#53
b100 4
b100 Q
b100 S
b101 ;
b101 [
b0 :
b0 Y
b1 ?
b1 W
b0 8
b0 D
b1 7
b1 R
b0 <
b101 =
b101 F
b100 .
b100 N
b10000000000000101 #
b10000000000000101 %
b100 >
b100 L
b100 O
#54
b101 0
b101 A
b101 H
13
1'
b0 6
b0 @
b0 E
#55
0&
b0 1
b0 G
b0 K
b0 (
b0 I
b0 U
b101 +
b101 C
b101 V
b1000 /
b1000 M
b1000 P
b0 ,
b0 J
b0 T
b0 Z
b0 -
b0 B
b0 X
0"
#60
1"
#61
b100 !
b100 9
#63
b1000 4
b1000 Q
b1000 S
b1 0
b1 A
b1 H
b1000 .
b1000 N
b1 ;
b1 [
b10 ?
b10 W
b1 8
b1 D
b10 7
b10 R
b1 =
b1 F
b1000 >
b1000 L
b1000 O
b1000000100000000000000001 #
b1000000100000000000000001 %
#64
b0 0
b0 A
b0 H
b1 +
b1 C
b1 V
03
#65
b101 0
b101 A
b101 H
1&
b101 1
b101 G
b101 K
b11111011 (
b11111011 I
b11111011 U
b0 +
b0 C
b0 V
b101 ,
b101 J
b101 T
b101 Z
b10000 /
b10000 M
b10000 P
0"
#66
0&
b101 +
b101 C
b101 V
#70
1"
#71
b1000 !
b1000 9
#73
b1100 4
b1100 Q
b1100 S
b0 ;
b0 [
b11 ?
b11 W
b110 8
b110 D
b11 7
b11 R
b0 =
b0 F
b1100 .
b1100 N
b110000000110000000000000000 #
b110000000110000000000000000 %
b1100 >
b1100 L
b1100 O
#74
b10000 .
b10000 N
x&
1*
bx +
bx C
bx V
12
0'
bx 6
bx @
bx E
#75
b0 0
b0 A
b0 H
b0 1
b0 G
b0 K
b0 (
b0 I
b0 U
b11000 .
b11000 N
b0 ,
b0 J
b0 T
b0 Z
b11000 /
b11000 M
b11000 P
0"
#80
1"
#81
b11000 !
b11000 9
#83
b100 ;
b100 [
b0 8
b0 D
b100 =
b100 F
b11100 >
b11100 L
b11100 O
b110000000000000100 #
b110000000000000100 %
#84
b11100 .
b11100 N
0*
b100 0
b100 A
b100 H
02
13
1'
b0 6
b0 @
b0 E
#85
0&
b100 +
b100 C
b100 V
b101000 /
b101000 M
b101000 P
0"
#90
1"
#91
b11100 !
b11100 9
#93
b10000 4
b10000 Q
b10000 S
b100 ?
b100 W
b100 7
b100 R
b100000 .
b100000 N
b1000000000000000100 #
b1000000000000000100 %
b100000 >
b100000 L
b100000 O
#95
b110000 /
b110000 M
b110000 P
0"
#100
1"
#101
b100000 !
b100000 9
#103
b11111111111111111111111111101100 4
b11111111111111111111111111101100 Q
b11111111111111111111111111101100 S
b100100 .
b100100 N
b11 :
b11 Y
b11 ?
b11 W
b111 8
b111 D
b11111011 7
b11111011 R
b11 <
b100100 >
b100100 L
b100100 O
b111111110110000001100000100 #
b111111110110000001100000100 %
#104
b11111100 0
b11111100 A
b11111100 H
b11111100 1
b11111100 G
b11111100 K
b11111100 (
b11111100 I
b11111100 U
15
03
1)
0'
b1 6
b1 @
b1 E
b100 ,
b100 J
b100 T
b100 Z
#105
b100 -
b100 B
b100 X
b10000 /
b10000 M
b10000 P
0"
#106
b10000 .
b10000 N
1*
1&
b0 +
b0 C
b0 V
#110
1"
#111
b10000 !
b10000 9
#113
b11000 4
b11000 Q
b11000 S
b10 ;
b10 [
b1 :
b1 Y
b110 ?
b110 W
b100 8
b100 D
b110 7
b110 R
b1 <
b10 =
b10 F
b100000001100000000100000010 #
b100000001100000000100000010 %
b10100 >
b10100 L
b10100 O
#114
b10100 .
b10100 N
0*
b100 0
b100 A
b100 H
b100 1
b100 G
b100 K
05
0)
1'
b10 6
b10 @
b10 E
#115
b101 0
b101 A
b101 H
0&
b101 1
b101 G
b101 K
b11111011 (
b11111011 I
b11111011 U
b100 +
b100 C
b100 V
b101 ,
b101 J
b101 T
b101 Z
b101 -
b101 B
b101 X
b101100 /
b101100 M
b101100 P
0"
#116
b101 +
b101 C
b101 V
#120
1"
#121
b10100 !
b10100 9
#123
b1100 4
b1100 Q
b1100 S
b11000 .
b11000 N
b11 ;
b11 [
b11 ?
b11 W
b111 8
b111 D
b11 7
b11 R
b11 =
b11 F
b11000 >
b11000 L
b11000 O
b111000000110000000100000011 #
b111000000110000000100000011 %
#124
b11111011 0
b11111011 A
b11111011 H
b11111011 1
b11111011 G
b11111011 K
15
1)
0'
b1 6
b1 @
b1 E
#125
b11111100 0
b11111100 A
b11111100 H
b11111100 1
b11111100 G
b11111100 K
b11111100 (
b11111100 I
b11111100 U
b100 ,
b100 J
b100 T
b100 Z
b100100 /
b100100 M
b100100 P
0"
#126
b1 +
b1 C
b1 V
#130
1"
#131
b11000 !
b11000 9
#133
b100 ;
b100 [
b0 :
b0 Y
b0 8
b0 D
b0 <
b100 =
b100 F
b11100 .
b11100 N
b110000000000000100 #
b110000000000000100 %
b11100 >
b11100 L
b11100 O
#134
b100 0
b100 A
b100 H
b100 1
b100 G
b100 K
05
13
0)
1'
b0 6
b0 @
b0 E
#135
b100 +
b100 C
b100 V
b0 -
b0 B
b0 X
b101000 /
b101000 M
b101000 P
0"
#140
1"
#141
b11100 !
b11100 9
#143
b10000 4
b10000 Q
b10000 S
b100000 .
b100000 N
b100 ?
b100 W
b100 7
b100 R
b100000 >
b100000 L
b100000 O
b1000000000000000100 #
b1000000000000000100 %
#145
b110000 /
b110000 M
b110000 P
0"
#150
1"
#151
b100000 !
b100000 9
#153
b11111111111111111111111111101100 4
b11111111111111111111111111101100 Q
b11111111111111111111111111101100 S
b11 :
b11 Y
b11 ?
b11 W
b111 8
b111 D
b11111011 7
b11111011 R
b11 <
b100100 .
b100100 N
b111111110110000001100000100 #
b111111110110000001100000100 %
b100100 >
b100100 L
b100100 O
